Metadata-Version: 1.0
Name: baidutrans
Version: 0.1
Summary: 百度翻译
Home-page: UNKNOWN
Author: panyian
Author-email: UNKNOWN
License: MIT
Platform: UNKNOWN
